LICENSE
README.md
setup.py
pitt_schemas/__init__.py
pitt_schemas/exceptions.py
pitt_schemas.egg-info/PKG-INFO
pitt_schemas.egg-info/SOURCES.txt
pitt_schemas.egg-info/dependency_links.txt
pitt_schemas.egg-info/not-zip-safe
pitt_schemas.egg-info/requires.txt
pitt_schemas.egg-info/top_level.txt
pitt_schemas/schemas/accession.json
pitt_schemas/schemas/agent.json
pitt_schemas/schemas/aurora_bag.json
pitt_schemas/schemas/base.json
pitt_schemas/schemas/collection.json
pitt_schemas/schemas/copyright_basis.json
pitt_schemas/schemas/date.json
pitt_schemas/schemas/digitization_bag.json
pitt_schemas/schemas/extent.json
pitt_schemas/schemas/external_identifier.json
pitt_schemas/schemas/group.json
pitt_schemas/schemas/language.json
pitt_schemas/schemas/legacy_digital_bag.json
pitt_schemas/schemas/license_basis.json
pitt_schemas/schemas/note.json
pitt_schemas/schemas/object.json
pitt_schemas/schemas/other_basis.json
pitt_schemas/schemas/reference.json
pitt_schemas/schemas/rights_basis_information.json
pitt_schemas/schemas/rights_granted.json
pitt_schemas/schemas/rights_statement.json
pitt_schemas/schemas/statute_basis.json
pitt_schemas/schemas/term.json