Metadata-Version: 2.1
Name: pitt-schemas
Version: 0.11
Summary: Pitt JSON Schemas and validators
Home-page: https://github.com/ulsdevteam/pitt_schemas
Author: University of Pittsburgh Library System, Systems Development
Author-email: uls-systemsdevelopment@pitt.edu
License: MIT
Platform: UNKNOWN
Classifier: Programming Language :: Python :: 3
Classifier: License :: OSI Approved :: MIT License
Classifier: Operating System :: OS Independent
Requires-Python: >=3.6
